bounceboard/__init__.py
bounceboard/app.py
bounceboard/common.py
bounceboard-0.1.0.dist-info/METADATA
bounceboard-0.1.0.dist-info/WHEEL
bounceboard-0.1.0.dist-info/entry_points.txt
bounceboard-0.1.0.dist-info/RECORD
