Metadata-Version: 2.4
Name: bounceboard
Version: 0.1.0
Summary: A command-line utility to synchronize clipboards across machines.
Project-URL: Documentation, https://github.com/quartzjer/bounceboard#readme
Project-URL: Source, https://github.com/quartzjer/bounceboard
Project-URL: Issues, https://github.com/quartzjer/bounceboard/issues
Author-email: Jeremie Miller <jeremie.miller@gmail.com>
License-Expression: MIT
Keywords: clipboard,pasteboard,sync,utility
Classifier: Environment :: Console
Classifier: License :: OSI Approved :: MIT License
Classifier: Operating System :: MacOS :: MacOS X
Classifier: Operating System :: POSIX :: Linux
Classifier: Programming Language :: Python :: 3
Classifier: Topic :: Utilities
Requires-Dist: aiohttp>=3.8.0
Requires-Dist: psutil>=5.8.0
Requires-Dist: pyperclip>=1.8.0
